keker/__init__.py
keker-0.0.1.dist-info/LICENSES.txt
keker-0.0.1.dist-info/METADATA
keker-0.0.1.dist-info/WHEEL
keker-0.0.1.dist-info/top_level.txt
keker-0.0.1.dist-info/RECORD
