Metadata-Version: 2.1
Name: keker
Version: 0.0.1
Summary: This package can make making checkers much easier and faster!
Author: Tufaah
Author-email: yazanemails@gmail.com
Keywords: checker,keker,scrape,java script scraper,scraper,accounts,crack,cracking
Classifier: Development Status :: 1 - Planning
Classifier: Intended Audience :: Developers
Classifier: Programming Language :: Python :: 3
Classifier: Operating System :: Unix
Classifier: Operating System :: MacOS :: MacOS X
Classifier: Operating System :: Microsoft :: Windows
License-File: LICENSES.txt
Requires-Dist: requests
